gpoints/__init__.py
gpoints/graph_points.py
gpoints-0.0.2.dist-info/METADATA
gpoints-0.0.2.dist-info/WHEEL
gpoints-0.0.2.dist-info/top_level.txt
gpoints-0.0.2.dist-info/RECORD
