Metadata-Version: 2.1
Name: gpoints
Version: 0.0.2
Summary: From graph Image as input, get corresponding points
Author: Ujjawal Kumar (India)
Author-email: <kumarujjawal3621@gmail.com>
Keywords: python,points,stock price,Image,numpy array
Classifier: Development Status :: 1 - Planning
Classifier: Intended Audience :: Developers
Classifier: Programming Language :: Python :: 3
Classifier: Operating System :: Unix
Classifier: Operating System :: MacOS :: MacOS X
Classifier: Operating System :: Microsoft :: Windows
